machine/annotations/__init__.py
machine/annotations/range.py
machine/clusterers/__init__.py
machine/clusterers/cluster.py
machine/clusterers/flat_clusterer.py
machine/clusterers/flat_upgma_clusterer.py
machine/clusterers/neighbor_joining_clusterer.py
machine/clusterers/rooted_hierarchical_clusterer.py
machine/clusterers/unrooted_hierarchical_clusterer.py
machine/clusterers/upgma_clusterer.py
machine/corpora/AllBiblicalTerms.xml
machine/corpora/BiblicalTerms.xml
machine/corpora/BiblicalTermsEn.xml
machine/corpora/BiblicalTermsEs.xml
machine/corpora/BiblicalTermsFr.xml
machine/corpora/BiblicalTermsId.xml
machine/corpora/BiblicalTermsP6NT.xml
machine/corpora/BiblicalTermsPt.xml
machine/corpora/BiblicalTermsSILNT.xml
machine/corpora/__init__.py
machine/corpora/aligned_word_pair.py
machine/corpora/alignment_collection.py
machine/corpora/alignment_corpus.py
machine/corpora/alignment_row.py
machine/corpora/corpora_utils.py
machine/corpora/corpus.py
machine/corpora/dbl_bundle_text_corpus.py
machine/corpora/dictionary_alignment_corpus.py
machine/corpora/dictionary_text_corpus.py
machine/corpora/file_paratext_project_settings_parser.py
machine/corpora/file_paratext_project_text_updater.py
machine/corpora/file_stream_container.py
machine/corpora/flatten.py
machine/corpora/memory_alignment_collection.py
machine/corpora/memory_stream_container.py
machine/corpora/memory_text.py
machine/corpora/multi_key_ref.py
machine/corpora/parallel_text_corpus.py
machine/corpora/parallel_text_row.py
machine/corpora/paratext_backup_terms_corpus.py
machine/corpora/paratext_backup_text_corpus.py
machine/corpora/paratext_project_settings.py
machine/corpora/paratext_project_settings_parser_base.py
machine/corpora/paratext_project_terms_parser_base.py
machine/corpora/paratext_project_text_updater_base.py
machine/corpora/paratext_text_corpus.py
machine/corpora/place_markers_usfm_update_block_handler.py
machine/corpora/scripture_element.py
machine/corpora/scripture_embed.py
sil_machine-1.8.4.dist-info/METADATA
sil_machine-1.8.4.dist-info/WHEEL
sil_machine-1.8.4.dist-info/licenses/LICENSE
sil_machine-1.8.4.dist-info/RECORD
