Metadata-Version: 2.4
Name: sil-machine
Version: 1.8.4
Summary: A natural language processing library that is focused on providing tools for resource-poor languages.
License: MIT
License-File: LICENSE
Keywords: machine,translation,natural,language,processing
Author: SIL International
Maintainer: Damien Daspit
Maintainer-email: damien_daspit@sil.org
Requires-Python: >=3.9,<3.13
Classifier: License :: OSI Approved :: MIT License
Classifier: Programming Language :: Python :: 3
Classifier: Programming Language :: Python :: 3.9
Classifier: Programming Language :: Python :: 3.10
Classifier: Programming Language :: Python :: 3.11
Classifier: Programming Language :: Python :: 3.12
Classifier: Topic :: Scientific/Engineering
Classifier: Topic :: Scientific/Engineering :: Artificial Intelligence
Classifier: Topic :: Scientific/Engineering :: Mathematics
Classifier: Topic :: Software Development
Classifier: Topic :: Software Development :: Libraries
Classifier: Topic :: Software Development :: Libraries :: Python Modules
Classifier: Topic :: Text Processing
Classifier: Topic :: Text Processing :: Linguistic
Provides-Extra: huggingface
Provides-Extra: jobs
Provides-Extra: sentencepiece
Provides-Extra: thot
Requires-Dist: boto3 (>=1.19.41,<2.0.0)
Requires-Dist: botocore (>=1.35.41,<2.0.0)
Requires-Dist: charset-normalizer (>=2.1.1,<3.0.0)
Requires-Dist: clearml[s3] (>=1.13.1,<2.0.0) ; extra == "jobs"
Requires-Dist: datasets (>=2.4.0,<3.0.0) ; extra == "huggingface"
Requires-Dist: dynaconf (>=3.2.5,<4.0.0) ; extra == "jobs"
Requires-Dist: eflomal (>=2.0.0,<3.0.0) ; (sys_platform == "linux") and (extra == "jobs")
Requires-Dist: json-stream (>=1.3.0,<2.0.0) ; extra == "jobs"
Requires-Dist: networkx (>=3,<4)
Requires-Dist: numpy (>=1.24.4,<2.0.0)
Requires-Dist: regex (>=2021.7.6)
Requires-Dist: sacremoses (>=0.0.53,<0.0.54) ; extra == "huggingface"
Requires-Dist: sentencepiece (>=0.2.0,<0.3.0) ; extra == "sentencepiece"
Requires-Dist: sil-thot (>=3.4.6,<4.0.0) ; extra == "thot"
Requires-Dist: sortedcontainers (>=2.4.0,<3.0.0)
Requires-Dist: transformers (==4.46.2) ; extra == "huggingface"
Requires-Dist: urllib3 (<2)
Project-URL: Repository, https://github.com/sillsdev/machine.py
